tn93/__init__.py
tn93/argparser.py
tn93/tn93.py
tn93-1.2.2.dist-info/METADATA
tn93-1.2.2.dist-info/WHEEL
tn93-1.2.2.dist-info/top_level.txt
tn93-1.2.2.dist-info/RECORD
