Metadata-Version: 2.1
Name: tn93
Version: 1.2.2
Summary: A python implementation of the Tamura-Nei pairwise distance calculation
Author-email: Reagan Kelly <ylb9@cdc.gov>
Project-URL: Homepage, https://github.com/CDCgov/tn93
Project-URL: Bug Tracker, https://github.com/CDCgov/tn93/issues
Classifier: Programming Language :: Python :: 3
Classifier: License :: OSI Approved :: MIT License
Classifier: Operating System :: OS Independent
Requires-Python: >=3.7
